infect_tools_noisy_conv.py
tree_tools.py
infect_net_inference-0.0.2.dist-info/LICENSE.txt
infect_net_inference-0.0.2.dist-info/METADATA
infect_net_inference-0.0.2.dist-info/WHEEL
infect_net_inference-0.0.2.dist-info/top_level.txt
infect_net_inference-0.0.2.dist-info/RECORD
